raspimonitor/__init__.py
raspimonitor/__main__.py
raspimonitor/raspimonitor.py
raspimonitor-0.0.2.dist-info/LICENSE
raspimonitor-0.0.2.dist-info/METADATA
raspimonitor-0.0.2.dist-info/WHEEL
raspimonitor-0.0.2.dist-info/entry_points.txt
raspimonitor-0.0.2.dist-info/top_level.txt
raspimonitor-0.0.2.dist-info/RECORD
