Metadata-Version: 2.1
Name: raspimonitor
Version: 0.0.2
Summary: Monitoring and alerting for your RaspberryPi 
Author: w0rmr1d3r
License: MIT
Project-URL: Homepage, https://github.com/w0rmr1d3r/raspimonitor
Project-URL: Repository, https://github.com/w0rmr1d3r/raspimonitor
Project-URL: Bug Tracker, https://github.com/w0rmr1d3r/raspimonitor/issues
Project-URL: Documentation, https://github.com/w0rmr1d3r/raspimonitor
Project-URL: Changelog, https://github.com/w0rmr1d3r/raspimonitor/releases
Project-URL: Funding, https://github.com/sponsors/w0rmr1d3r
Keywords: raspberry,raspberrypi,pi,monitor
Classifier: Programming Language :: Python
Classifier: Programming Language :: Python :: 3
Classifier: Programming Language :: Python :: 3 :: Only
Classifier: Programming Language :: Python :: 3.9
Classifier: Intended Audience :: Developers
Classifier: Intended Audience :: Information Technology
Classifier: Intended Audience :: System Administrators
Classifier: License :: OSI Approved :: MIT License
Requires-Python: ~=3.9.0
License-File: LICENSE
Requires-Dist: requests ~=2.0
Provides-Extra: dev
Requires-Dist: pip-tools ~=7.0 ; extra == 'dev'
Requires-Dist: pytest ~=8.0 ; extra == 'dev'
Requires-Dist: ruff ==0.3.7 ; extra == 'dev'
